{".class": "MypyFile", "_fullname": "lib.app.input_converters.converters.coco_converters.sa_pixel_to_coco", "is_partial_stub_package": false, "is_stub": false, "names": {".class": "SymbolTable", "__doc__": {".class": "SymbolTableNode", "kind": "Gdef", "node": {".class": "Var", "flags": ["is_ready"], "fullname": "lib.app.input_converters.converters.coco_converters.sa_pixel_to_coco.__doc__", "name": "__doc__", "type": "builtins.str"}}, "__file__": {".class": "SymbolTableNode", "kind": "Gdef", "node": {".class": "Var", "flags": ["is_ready"], "fullname": "lib.app.input_converters.converters.coco_converters.sa_pixel_to_coco.__file__", "name": "__file__", "type": "builtins.str"}}, "__instance_object_commons_per_instance": {".class": "SymbolTableNode", "kind": "Gdef", "node": {".class": "FuncDef", "arg_kinds": [0, 0, 0], "arg_names": ["instance", "id_generator", "flat_mask"], "flags": [], "fullname": "lib.app.input_converters.converters.coco_converters.sa_pixel_to_coco.__instance_object_commons_per_instance", "name": "__instance_object_commons_per_instance", "type": null}}, "__name__": {".class": "SymbolTableNode", "kind": "Gdef", "node": {".class": "Var", "flags": ["is_ready"], "fullname": "lib.app.input_converters.converters.coco_converters.sa_pixel_to_coco.__name__", "name": "__name__", "type": "builtins.str"}}, "__package__": {".class": "SymbolTableNode", "kind": "Gdef", "node": {".class": "Var", "flags": ["is_ready"], "fullname": "lib.app.input_converters.converters.coco_converters.sa_pixel_to_coco.__package__", "name": "__package__", "type": "builtins.str"}}, "_area": {".class": "SymbolTableNode", "cross_ref": "lib.app.input_converters.converters.coco_converters.coco_api._area", "kind": "Gdef"}, "_toBbox": {".class": "SymbolTableNode", "cross_ref": "lib.app.input_converters.converters.coco_converters.coco_api._toBbox", "kind": "Gdef"}, "cv": {".class": "SymbolTableNode", "kind": "Gdef", "node": {".class": "Var", "flags": ["is_suppressed_import", "is_ready"], "fullname": "lib.app.input_converters.converters.coco_converters.sa_pixel_to_coco.cv", "name": "cv", "type": {".class": "AnyType", "missing_import_name": "lib.app.input_converters.converters.coco_converters.sa_pixel_to_coco.cv", "source_any": null, "type_of_any": 3}}}, "instance_object_commons": {".class": "SymbolTableNode", "kind": "Gdef", "node": {".class": "FuncDef", "arg_kinds": [0, 0, 0], "arg_names": ["instances", "id_generator", "flat_mask"], "flags": [], "fullname": "lib.app.input_converters.converters.coco_converters.sa_pixel_to_coco.instance_object_commons", "name": "instance_object_commons", "type": null}}, "np": {".class": "SymbolTableNode", "cross_ref": "numpy", "kind": "Gdef"}, "sa_pixel_to_coco_instance_segmentation": {".class": "SymbolTableNode", "kind": "Gdef", "node": {".class": "FuncDef", "arg_kinds": [0, 0, 0, 0], "arg_names": ["make_annotation", "image_commons", "instances", "id_generator"], "flags": [], "fullname": "lib.app.input_converters.converters.coco_converters.sa_pixel_to_coco.sa_pixel_to_coco_instance_segmentation", "name": "sa_pixel_to_coco_instance_segmentation", "type": null}}, "sa_pixel_to_coco_panoptic_segmentation": {".class": "SymbolTableNode", "kind": "Gdef", "node": {".class": "FuncDef", "arg_kinds": [0, 0, 0], "arg_names": ["image_commons", "instnaces", "id_generator"], "flags": [], "fullname": "lib.app.input_converters.converters.coco_converters.sa_pixel_to_coco.sa_pixel_to_coco_panoptic_segmentation", "name": "sa_pixel_to_coco_panoptic_segmentation", "type": null}}}, "path": "lib/app/input_converters/converters/coco_converters/sa_pixel_to_coco.py"}